pahotoolkit/__init__.py
pahotoolkit/client.py
pahotoolkit/exc.py
pahotoolkit/log.py
pahotoolkit/on_connect.py
pahotoolkit/subscriptions.py
pahotoolkit/utils.py
pahotoolkitfork/__init__.py
pahotoolkitfork/client.py
pahotoolkitfork/exc.py
pahotoolkitfork/log.py
pahotoolkitfork/on_connect.py
pahotoolkitfork/subscriptions.py
pahotoolkitfork/utils.py
pahotoolkitfork-0.1.4.dist-info/LICENSE
pahotoolkitfork-0.1.4.dist-info/METADATA
pahotoolkitfork-0.1.4.dist-info/WHEEL
pahotoolkitfork-0.1.4.dist-info/top_level.txt
pahotoolkitfork-0.1.4.dist-info/RECORD
