Metadata-Version: 2.1
Name: pahotoolkitfork
Version: 0.1.4
Summary: Paho's MQTT dev Toolkit
Home-page: https://bitbucket.org/kiotsystem/paho-toolkit
Author: Arnulfo Solis
Author-email: arnulfojr94@gmail.com
License: UNKNOWN
Keywords: paho,eclipse,mqtt,toolkit,framework
Platform: any
Classifier: Intended Audience :: Developers
Classifier: License :: OSI Approved :: MIT License
Classifier: Operating System :: OS Independent
Classifier: Programming Language :: Python
Classifier: Programming Language :: Python :: 3
Classifier: Programming Language :: Python :: 3.5
Classifier: Programming Language :: Python :: 3.6
Classifier: Programming Language :: Python :: 3.7
Classifier: Programming Language :: Python :: Implementation :: CPython
Classifier: Programming Language :: Python :: Implementation :: PyPy
Classifier: Topic :: Internet :: WWW/HTTP :: Dynamic Content
Classifier: Topic :: Software Development :: Libraries :: Python Modules
Requires-Dist: paho-mqtt (==1.4.0)
